cdpify/__init__.py
cdpify/client.py
cdpify/exceptions.py
cdpify/logging.py
cdpify/domains/__init__.py
cdpify/domains/accessibility/__init__.py
cdpify/domains/accessibility/client.py
cdpify/domains/accessibility/commands.py
cdpify/domains/accessibility/events.py
cdpify/domains/accessibility/types.py
cdpify/domains/animation/__init__.py
cdpify/domains/animation/client.py
cdpify/domains/animation/commands.py
cdpify/domains/animation/events.py
cdpify/domains/animation/types.py
cdpify/domains/audits/__init__.py
cdpify/domains/audits/client.py
cdpify/domains/audits/commands.py
cdpify/domains/audits/events.py
cdpify/domains/audits/types.py
cdpify/domains/backgroundservice/__init__.py
cdpify/domains/backgroundservice/client.py
cdpify/domains/backgroundservice/commands.py
cdpify/domains/backgroundservice/events.py
cdpify/domains/backgroundservice/types.py
cdpify/domains/browser/__init__.py
cdpify/domains/browser/client.py
cdpify/domains/browser/commands.py
cdpify/domains/browser/events.py
cdpify/domains/browser/types.py
cdpify/domains/cachestorage/__init__.py
cdpify/domains/cachestorage/client.py
cdpify/domains/cachestorage/commands.py
cdpify/domains/cachestorage/events.py
cdpify/domains/cachestorage/types.py
cdpify/domains/cast/__init__.py
cdpify/domains/cast/client.py
cdpify/domains/cast/commands.py
cdpify/domains/cast/events.py
cdpify/domains/cast/types.py
cdpify/domains/console/__init__.py
cdpify/domains/console/client.py
cdpify/domains/console/commands.py
cdpify/domains/console/events.py
cdpify/domains/console/types.py
cdpify/domains/css/__init__.py
cdpify/domains/css/client.py
cdpify/domains/css/commands.py
cdpify/domains/css/events.py
cdpify/domains/css/types.py
cdpify/domains/debugger/__init__.py
cdpify/domains/debugger/client.py
cdpify/domains/debugger/commands.py
cdpify/domains/debugger/events.py
cdpify/domains/debugger/types.py
cdpify/domains/deviceorientation/__init__.py
cdpify/domains/deviceorientation/client.py
cdpify/domains/deviceorientation/commands.py
cdpify-0.2.2.dist-info/METADATA
cdpify-0.2.2.dist-info/WHEEL
cdpify-0.2.2.dist-info/top_level.txt
cdpify-0.2.2.dist-info/RECORD
