Metadata-Version: 2.4
Name: cdpify
Version: 0.2.2
Summary: Add your description here
Requires-Python: >=3.13
Requires-Dist: httpx>=0.28.1
Requires-Dist: pre-commit>=4.5.1
Requires-Dist: pydantic>=2.12.5
Requires-Dist: websockets>=15.0.1
